TSmodel/__init__.py
TSmodel-0.2.dist-info/LICENCE.txt
TSmodel-0.2.dist-info/METADATA
TSmodel-0.2.dist-info/WHEEL
TSmodel-0.2.dist-info/top_level.txt
TSmodel-0.2.dist-info/RECORD
